mission_control/__init__.py
mission_control/__main__.py
mission_control/alert_finder.py
mission_control/cli.py
mission_control/main_helper.py
mission_control/message_processor.py
mission_control/models.py
mission_control/output_formatter.py
mission_control/telemetry_file_parser.py
mission_control/telemetry_processor.py
tests/__init__.py
tests/test_alert_finder.py
tests/test_cli.py
tests/test_message_processor.py
tests/test_output_formatter.py
tests/test_telemetry_file_parser.py
tests/test_telemetry_processor.py
mission_control-0.0.4.dist-info/LICENSE
mission_control-0.0.4.dist-info/METADATA
mission_control-0.0.4.dist-info/WHEEL
mission_control-0.0.4.dist-info/entry_points.txt
mission_control-0.0.4.dist-info/top_level.txt
mission_control-0.0.4.dist-info/RECORD
