Metadata-Version: 2.1
Name: mission-control
Version: 0.0.4
Summary: Mission Control Satellite Telemetry Processor
Home-page: https://gitlab.com/pt-arvind/paging-mission-control
Author: Arvind Subramanian
Author-email: pt.arvind@gmail.com
License: UNKNOWN
Platform: UNKNOWN
Classifier: Programming Language :: Python :: 3
Classifier: License :: OSI Approved :: MIT License
Classifier: Operating System :: OS Independent
Requires-Python: >=3.8.2
